openapi_python_client/__init__.py
openapi_python_client/__main__.py
openapi_python_client/cli.py
openapi_python_client/config.py
openapi_python_client/py.typed
openapi_python_client/utils.py
openapi_python_client/parser/__init__.py
openapi_python_client/parser/bodies.py
openapi_python_client/parser/errors.py
openapi_python_client/parser/openapi.py
openapi_python_client/parser/responses.py
openapi_python_client/parser/properties/__init__.py
openapi_python_client/parser/properties/any.py
openapi_python_client/parser/properties/boolean.py
openapi_python_client/parser/properties/const.py
openapi_python_client/parser/properties/date.py
openapi_python_client/parser/properties/datetime.py
openapi_python_client/parser/properties/enum_property.py
openapi_python_client/parser/properties/file.py
openapi_python_client/parser/properties/float.py
openapi_python_client/parser/properties/int.py
openapi_python_client/parser/properties/list_property.py
openapi_python_client/parser/properties/literal_enum_property.py
openapi_python_client/parser/properties/merge_properties.py
openapi_python_client/parser/properties/model_property.py
openapi_python_client/parser/properties/none.py
openapi_python_client/parser/properties/property.py
openapi_python_client/parser/properties/protocol.py
openapi_python_client/parser/properties/schemas.py
openapi_python_client/parser/properties/string.py
openapi_python_client/parser/properties/union.py
openapi_python_client/parser/properties/uuid.py
openapi_python_client/schema/3.0.3.md
openapi_python_client/schema/3.1.0.md
openapi_python_client/schema/__init__.py
openapi_python_client/schema/data_type.py
openapi_python_client/schema/parameter_location.py
openapi_python_client/schema/openapi_schema_pydantic/LICENSE
openapi_python_client/schema/openapi_schema_pydantic/README.md
openapi_python_client/schema/openapi_schema_pydantic/__init__.py
openapi_python_client/schema/openapi_schema_pydantic/callback.py
openapi_python_client-0.27.1.dist-info/METADATA
openapi_python_client-0.27.1.dist-info/WHEEL
openapi_python_client-0.27.1.dist-info/entry_points.txt
openapi_python_client-0.27.1.dist-info/licenses/LICENSE
openapi_python_client-0.27.1.dist-info/RECORD
